setup.py
frasco_trello/__init__.py
frasco_trello/blueprint.py
frasco_trello.egg-info/PKG-INFO
frasco_trello.egg-info/SOURCES.txt
frasco_trello.egg-info/dependency_links.txt
frasco_trello.egg-info/not-zip-safe
frasco_trello.egg-info/requires.txt
frasco_trello.egg-info/top_level.txt