Metadata-Version: 1.0
Name: frasco-trello
Version: 0.1
Summary: Trello integration for Frasco
Home-page: http://github.com/frascoweb/frasco-trello
Author: Maxime Bouroumeau-Fuseau
Author-email: maxime.bouroumeau@gmail.com
License: MIT
Platform: any
